{

  "comments": [
  {
    "user": {
      "id": 842075,
        "first_name": "Learned Evolution",
        "last_name": "",
        "username": "LearnedEvolution",
        "city": "Brooklyn",
        "state": "New York",
        "country": "United States",
        "company": "Learned Evolution",
        "occupation": "",
        "created_on": 1325878952,
        "url": "http://www.behance.net/LearnedEvolution",
        "display_name": "Learned Evolution",
        "images": {
          "32": "http://behance.vo.llnwd.net/profiles8/842075/32x9acd77e69f02d29248fc8600232ce034.png",
          "50": "http://behance.vo.llnwd.net/profiles8/842075/50x9acd77e69f02d29248fc8600232ce034.png",
          "78": "http://behance.vo.llnwd.net/profiles8/842075/78x9acd77e69f02d29248fc8600232ce034.png",
          "115": "http://behance.vo.llnwd.net/profiles8/842075/115x9acd77e69f02d29248fc8600232ce034.png",
          "129": "http://behance.vo.llnwd.net/profiles8/842075/129x9acd77e69f02d29248fc8600232ce034.png",
          "138": "http://behance.vo.llnwd.net/profiles8/842075/9acd77e69f02d29248fc8600232ce034.png"
        },
        "fields": [
          "Design",
        "Marketing",
        "Video Arts"
          ]
    },
      "comment": "It's the Bible at our office! One of the most inspiring books out there!",
      "created_on": 1345478249
  },
  {
    "user": {
      "id": 183493,
      "first_name": "Fahim",
      "last_name": "MD",
      "username": "workoffahimmd",
      "city": "Toronto",
      "state": "Ontario",
      "country": "Canada",
      "company": "Work Of Fahim MD",
      "occupation": "Creative Designer",
      "created_on": 1277406314,
      "url": "http://www.behance.net/workoffahimmd",
      "display_name": "Fahim MD",
      "images": {
        "32": "http://behance.vo.llnwd.net/profiles4/183493/32x661ae522810f714aa781c7224970ae91.png",
        "50": "http://behance.vo.llnwd.net/profiles4/183493/50x661ae522810f714aa781c7224970ae91.png",
        "78": "http://behance.vo.llnwd.net/profiles4/183493/78x661ae522810f714aa781c7224970ae91.png",
        "115": "http://behance.vo.llnwd.net/profiles4/183493/115x661ae522810f714aa781c7224970ae91.png",
        "129": "http://behance.vo.llnwd.net/profiles4/183493/129x661ae522810f714aa781c7224970ae91.png",
        "138": "http://behance.vo.llnwd.net/profiles4/183493/661ae522810f714aa781c7224970ae91.png"
      },
      "fields": [
        "Branding",
      "User Interface Design",
      "Web Design"
        ]
    },
    "comment": "Great book, almost done reading...",
    "created_on": 1340560157
  },
  {
    "user": {
      "id": 262192,
      "first_name": "Leffe",
      "last_name": "Goldstein",
      "username": "leffegoldstein",
      "city": "Utrecht",
      "state": "",
      "country": "Netherlands",
      "company": "LeffeGoldstein",
      "occupation": "Senior Designer",
      "created_on": 1289894043,
      "url": "http://www.behance.net/leffegoldstein",
      "display_name": "Leffe Goldstein",
      "images": {
        "32": "http://behance.vo.llnwd.net/profiles21/262192/32x69636680862489b73acec6db57f59fc5.png",
        "50": "http://behance.vo.llnwd.net/profiles21/262192/50x69636680862489b73acec6db57f59fc5.png",
        "78": "http://behance.vo.llnwd.net/profiles21/262192/78x69636680862489b73acec6db57f59fc5.png",
        "115": "http://behance.vo.llnwd.net/profiles21/262192/115x69636680862489b73acec6db57f59fc5.png",
        "129": "http://behance.vo.llnwd.net/profiles21/262192/129x69636680862489b73acec6db57f59fc5.png",
        "138": "http://behance.vo.llnwd.net/profiles21/262192/69636680862489b73acec6db57f59fc5.png"
      },
      "fields": [
        "Graphic Design",
      "Packaging",
      "Toy Design"
        ]
    },
    "comment": "mesmerize...\n",
    "created_on": 1340042819
  },
  {
    "user": {
      "id": 92027,
      "first_name": "Mikaela",
      "last_name": "Rehnmark",
      "username": "MikaelaRehnmark",
      "city": "Gothenburg",
      "state": "",
      "country": "Sweden",
      "company": "R-ID",
      "occupation": "Founder & Industrial Designer",
      "created_on": 1232297857,
      "url": "http://www.behance.net/MikaelaRehnmark",
      "display_name": "Mikaela Rehnmark",
      "images": {
        "32": "http://behance.vo.llnwd.net/profiles3/92027/32xb7b5dacaaee1ef23f66e70e1f882083b.jpg",
        "50": "http://behance.vo.llnwd.net/profiles3/92027/50xb7b5dacaaee1ef23f66e70e1f882083b.jpg",
        "78": "http://behance.vo.llnwd.net/profiles3/92027/78xb7b5dacaaee1ef23f66e70e1f882083b.jpg",
        "115": "http://behance.vo.llnwd.net/profiles3/92027/115xb7b5dacaaee1ef23f66e70e1f882083b.jpg",
        "129": "http://behance.vo.llnwd.net/profiles3/92027/129xb7b5dacaaee1ef23f66e70e1f882083b.jpg",
        "138": "http://behance.vo.llnwd.net/profiles3/92027/b7b5dacaaee1ef23f66e70e1f882083b.jpg"
      },
      "fields": [
        "Industrial Design",
      "Product Design"
        ]
    },
    "comment": "Very inspiring book! ",
    "created_on": 1339073552
  },
  {
    "user": {
      "id": 50004,
      "first_name": "Scott",
      "last_name": "Belsky",
      "username": "sbelsky",
      "city": "New York",
      "state": "New York",
      "country": "United States",
      "company": "Behance LLC",
      "occupation": "CEO",
      "created_on": 1182480652,
      "url": "http://www.behance.net/sbelsky",
      "display_name": "Scott Belsky",
      "images": {
        "32": "http://behance.vo.llnwd.net/profiles/50004/32x0500041182480801.jpg",
        "50": "http://behance.vo.llnwd.net/profiles/50004/50x0500041182480801.jpg",
        "78": "http://behance.vo.llnwd.net/profiles/50004/78x0500041182480801.jpg",
        "115": "http://behance.vo.llnwd.net/profiles/50004/115x0500041182480801.jpg",
        "129": "http://behance.vo.llnwd.net/profiles/50004/129x0500041182480801.jpg",
        "138": "http://behance.vo.llnwd.net/profiles/50004/0500041182480801.jpg"
      },
      "fields": [
        "Entrepreneurship",
      "Furniture Design",
      "Writing"
        ]
    },
    "comment": "Thanks all for the kind comments...",
    "created_on": 1338944623
  },
  {
    "user": {
      "id": 215283,
      "first_name": "Beejay",
      "last_name": "Elles",
      "username": "beejayelles",
      "city": "Madison",
      "state": "Indiana",
      "country": "United States",
      "company": "Freelance Graphic Designer",
      "occupation": "Graphic Designer / Printshop Press and Bindery Operator",
      "created_on": 1281725289,
      "url": "http://www.behance.net/beejayelles",
      "display_name": "Beejay Elles",
      "images": {
        "32": "http://behance.vo.llnwd.net/profiles4/215283/32x36a09b7e5f571150ee8917086bef35d2.png",
        "50": "http://behance.vo.llnwd.net/profiles4/215283/50x36a09b7e5f571150ee8917086bef35d2.png",
        "78": "http://behance.vo.llnwd.net/profiles4/215283/78x36a09b7e5f571150ee8917086bef35d2.png",
        "115": "http://behance.vo.llnwd.net/profiles4/215283/115x36a09b7e5f571150ee8917086bef35d2.png",
        "129": "http://behance.vo.llnwd.net/profiles4/215283/129x36a09b7e5f571150ee8917086bef35d2.png",
        "138": "http://behance.vo.llnwd.net/profiles4/215283/36a09b7e5f571150ee8917086bef35d2.png"
      },
      "fields": [
        "Graphic Design",
      "Illustration",
      "Typography"
        ]
    },
    "comment": "Currently reading this, and the action method has been great for those projects that I just get stuck on. Great Work!",
    "created_on": 1337996145
  },
  {
    "user": {
      "id": 580775,
      "first_name": "Matthew",
      "last_name": "Prosser",
      "username": "matthewprosser",
      "city": "Cheltenham",
      "state": "",
      "country": "United Kingdom",
      "company": "",
      "occupation": "Junior Art director @ Saatchi & Saatchi",
      "created_on": 1312831337,
      "url": "http://www.behance.net/matthewprosser",
      "display_name": "Matthew Prosser",
      "images": {
        "32": "http://behance.vo.llnwd.net/profiles11/580775/32xe1eda5227fadcca0adc27ddaa14f0328.jpg",
        "50": "http://behance.vo.llnwd.net/profiles11/580775/50xe1eda5227fadcca0adc27ddaa14f0328.jpg",
        "78": "http://behance.vo.llnwd.net/profiles11/580775/78xe1eda5227fadcca0adc27ddaa14f0328.jpg",
        "115": "http://behance.vo.llnwd.net/profiles11/580775/115xe1eda5227fadcca0adc27ddaa14f0328.jpg",
        "129": "http://behance.vo.llnwd.net/profiles11/580775/129xe1eda5227fadcca0adc27ddaa14f0328.jpg",
        "138": "http://behance.vo.llnwd.net/profiles11/580775/e1eda5227fadcca0adc27ddaa14f0328.jpg"
      },
      "fields": [
        "Art Direction",
      "Branding",
      "Graphic Design"
        ]
    },
    "comment": "Got it at the start of my 3rd year this academic year. Sorted me right out work wise and nailed my work without getting as stressed. My girlfriend read it and she studies Law and got a lot from it to. Definitely a must read for students who want to hit the ground running. Big thanks!!",
    "created_on": 1333652063
  },
  {
    "user": {
      "id": 675890,
      "first_name": "JY",
      "last_name": "Houle",
      "username": "jyh",
      "city": "Montreal",
      "state": "Quebec",
      "country": "Canada",
      "company": "",
      "occupation": "Graphic Designer",
      "created_on": 1317750253,
      "url": "http://www.behance.net/jyh",
      "display_name": "JY Houle",
      "images": {
        "32": "http://behance.vo.llnwd.net/profiles26/675890/32x754230899659e33e19b90b2f15c17a4b.jpg",
        "50": "http://behance.vo.llnwd.net/profiles26/675890/50x754230899659e33e19b90b2f15c17a4b.jpg",
        "78": "http://behance.vo.llnwd.net/profiles26/675890/78x754230899659e33e19b90b2f15c17a4b.jpg",
        "115": "http://behance.vo.llnwd.net/profiles26/675890/115x754230899659e33e19b90b2f15c17a4b.jpg",
        "129": "http://behance.vo.llnwd.net/profiles26/675890/129x754230899659e33e19b90b2f15c17a4b.jpg",
        "138": "http://behance.vo.llnwd.net/profiles26/675890/754230899659e33e19b90b2f15c17a4b.jpg"
      },
      "fields": [
        "Art Direction",
      "Graphic Design",
      "Web Design"
        ]
    },
    "comment": "Just finished reading it, great inspiration, thanks",
    "created_on": 1331510075
  },
  {
    "user": {
      "id": 924651,
      "first_name": "Andika Prasetia",
      "last_name": "Putra",
      "username": "dikadig",
      "city": "Jakarta",
      "state": "",
      "country": "Indonesia",
      "company": "Satoe Indonesia",
      "occupation": "Student",
      "created_on": 1328798011,
      "url": "http://www.behance.net/dikadig",
      "display_name": "Andika Prasetia Putra",
      "images": {
        "32": "http://assets.behance.net/img/profile/no-image-32.jpg",
        "50": "http://assets.behance.net/img/profile/no-image-50.jpg",
        "78": "http://assets.behance.net/img/profile/no-image-78.jpg",
        "115": "http://assets.behance.net/img/profile/no-image-138.jpg",
        "129": "http://assets.behance.net/img/profile/no-image-138.jpg",
        "138": "http://assets.behance.net/img/profile/no-image-138.jpg"
      },
      "fields": [
        "Branding"
        ]
    },
    "comment": "You all should read this book!",
    "created_on": 1329308273
  }
  ]

}
